dbt/__init__.py
dbt/adapters/__init__.py
dbt/adapters/vertica/__init__.py
dbt/adapters/vertica/__version__.py
dbt/adapters/vertica/column.py
dbt/adapters/vertica/connections.py
dbt/adapters/vertica/impl.py
dbt/adapters/vertica/relation.py
dbt/adapters/vertica/relation_configs/__init__.py
dbt/adapters/vertica/relation_configs/policies.py
dbt/include/__init__.py
dbt/include/vertica/__init__.py
dbt/include/vertica/dbt_project.yml
dbt/include/vertica/profile_template.yml
dbt/include/vertica/sample_profiles.yml
dbt/include/vertica/macros/adapters/apply_grants.sql
dbt/include/vertica/macros/adapters/catalog.sql
dbt/include/vertica/macros/adapters/columns.sql
dbt/include/vertica/macros/adapters/freshness.sql
dbt/include/vertica/macros/adapters/indexes.sql
dbt/include/vertica/macros/adapters/metadata.sql
dbt/include/vertica/macros/adapters/persist_docs.sql
dbt/include/vertica/macros/adapters/relation.sql
dbt/include/vertica/macros/adapters/schema.sql
dbt/include/vertica/macros/materializations/clone.sql
dbt/include/vertica/macros/materializations/configs.sql
dbt/include/vertica/macros/materializations/hooks.sql
dbt/include/vertica/macros/materializations/models/incremental/helpers.sql
dbt/include/vertica/macros/materializations/models/incremental/incremental.sql
dbt/include/vertica/macros/materializations/models/incremental/is_incremental.sql
dbt/include/vertica/macros/materializations/models/incremental/merge.sql
dbt/include/vertica/macros/materializations/models/incremental/on_schema_change.sql
dbt/include/vertica/macros/materializations/models/incremental/strategies.sql
dbt/include/vertica/macros/materializations/models/table/create_table_as.sql
dbt/include/vertica/macros/materializations/models/table/table.sql
dbt/include/vertica/macros/materializations/models/view/create_or_replace_view.sql
dbt/include/vertica/macros/materializations/models/view/create_view_as.sql
dbt/include/vertica/macros/materializations/models/view/view.sql
dbt_vertica-1.8.5.dist-info/licenses/LICENSE
dbt_vertica-1.8.5.dist-info/METADATA
dbt_vertica-1.8.5.dist-info/WHEEL
dbt_vertica-1.8.5.dist-info/top_level.txt
dbt_vertica-1.8.5.dist-info/RECORD
