Metadata-Version: 2.4
Name: dbt-vertica
Version: 1.8.5
Summary: Official vertica adapter plugin for dbt (data build tool)
Home-page: https://github.com/ajay.abrol2/dbt-vertica/
Author: Vertica (Former authors: Matthew Carter, Andy Regan, Andrew Hedengren)
Author-email: os_dbt_vertica@microfocus.com
License: Apache License 2.0
Classifier: Development Status :: 5 - Production/Stable
Classifier: License :: OSI Approved :: Apache Software License
Classifier: Programming Language :: Python
Classifier: Programming Language :: Python :: 3
Classifier: Topic :: Database
Classifier: Topic :: Database :: Database Engines/Servers
Classifier: Topic :: Database :: Front-Ends
Classifier: Topic :: Software Development :: Libraries :: Python Modules
Classifier: Operating System :: OS Independent
Requires-Python: >=3.8.0
License-File: LICENSE
Requires-Dist: dbt-core==1.8.5
Requires-Dist: vertica-python>=1.1.0
Requires-Dist: dbt-tests-adapter==1.8.0
Requires-Dist: python-dotenv==0.21.1
Requires-Dist: pytest>=8.3.2
Dynamic: author
Dynamic: author-email
Dynamic: classifier
Dynamic: description
Dynamic: description-content-type
Dynamic: home-page
Dynamic: license
Dynamic: license-file
Dynamic: requires-dist
Dynamic: requires-python
Dynamic: summary
